not_grep/__init__.py
not_grep/_config.py
not_grep/_plugin_loader.py
not_grep/_run_checks.py
not_grep/checkers.py
not_grep-1.0.0.data/data/CHANGELOG.rst
not_grep-1.0.0.data/data/LICENSE
not_grep-1.0.0.data/data/README.rst
not_grep-1.0.0.data/data/requirements.txt
not_grep-1.0.0.dist-info/LICENSE
not_grep-1.0.0.dist-info/METADATA
not_grep-1.0.0.dist-info/WHEEL
not_grep-1.0.0.dist-info/entry_points.txt
not_grep-1.0.0.dist-info/top_level.txt
not_grep-1.0.0.dist-info/RECORD
