Metadata-Version: 2.1
Name: not-grep
Version: 1.0.0
Summary: kinda like grep but not quite
Home-page: https://github.com/mattsb42-meta/not-grep
Author: Matt Bullock
Author-email: m@ttsb42.com
Maintainer: Matt Bullock
License: Apache 2.0
Keywords: not-grep not_grep
Platform: UNKNOWN
Classifier: Development Status :: 5 - Production/Stable
Classifier: Intended Audience :: Developers
Classifier: Topic :: Utilities
Classifier: Natural Language :: English
Classifier: License :: OSI Approved :: Apache Software License
Classifier: Programming Language :: Python
Classifier: Programming Language :: Python :: 3
Classifier: Programming Language :: Python :: 3.6
Classifier: Programming Language :: Python :: 3.7
Classifier: Programming Language :: Python :: 3.8
Classifier: Programming Language :: Python :: Implementation :: CPython
Requires-Dist: click (>=7.1.1)
Requires-Dist: attrs (>=19.3.0)
Requires-Dist: toml (>=0.10.0)
Requires-Dist: setuptools
